{
  "id": "3590507012167195824",
  "timestamp": "2025-03-17T20:03:31.000Z",
  "caption": "E a lindeza que ficou o quarto da baby Bianca?! 😍\nMargaridas me pegam! Eu amei o resultado! E você, o que achou?\n\nObrigada, Nanda, pela confiança do nosso segundo projeto! 💜\n\n#arteemparede #pinturaartistica #quartomenina #quartoflores #quartomargaridas #decoracaoinfantil #arquiteturasalvador",
  "hashtags": [
    "arteemparede",
    "pinturaartistica",
    "quartomenina",
    "quartoflores",
    "quartomargaridas",
    "decoracaoinfantil",
    "arquiteturasalvador"
  ],
  "location": "Salvador, Bahia, Brazil",
  "likes": 68,
  "comments": 8,
  "media": [
    {
      "type": "image",
      "fileName": "e_a_lindeza_que_ficou_o_quarto_da_baby_bianca_margaridas_me_pegam_eu_amei_o_resultado_e_0.jpg"
    },
    {
      "type": "image",
      "fileName": "e_a_lindeza_que_ficou_o_quarto_da_baby_bianca_margaridas_me_pegam_eu_amei_o_resultado_e_1.jpg"
    },
    {
      "type": "image",
      "fileName": "e_a_lindeza_que_ficou_o_quarto_da_baby_bianca_margaridas_me_pegam_eu_amei_o_resultado_e_2.jpg"
    },
    {
      "type": "image",
      "fileName": "e_a_lindeza_que_ficou_o_quarto_da_baby_bianca_margaridas_me_pegam_eu_amei_o_resultado_e_3.jpg"
    }
  ],
  "categoria": "Outros",
  "subcategoria": "Geral",
  "descricao": "Conteúdo não categorizado"
}